{
  "project": {
    "name": "ArcSphere3D",
    "registration_date": "2026-05-14",
    "start_date": "2026-05-14",
    "release_deadline": "2026-11-14",
    "duration_months": 6,
    "days_remaining": 171,
    "registered_at": "2026-05-14",
    "phase_mode": "development",
    "goal_type": "mvp-release",
    "release_milestone": "ArcSphere3D v1.0.0 (Production Release)"
  },
  "goal": "セッション 2026-05-29: Issue #238 E2E 連鎖失敗の真因修正 (PR #239 merge 済み) + Issue #240 K8s kustomize base (PR #241 open, CI 実行中)。",
  "phase": "Verify",
  "mvp": {
    "definition": [
      "3D Viewer (Three.js + OrbitControls + GridHelper)",
      "STL / OBJ / glTF Loader",
      "Basic Edit (Transform: Move / Rotate / Scale)",
      "WebUI Management (Header / LeftMenu / Viewport / RightPanel / BottomConsole)",
      "Authentication scaffolding (JWT; Entra ID は post-MVP)"
    ],
    "target_demo_date": "2026-07-15",
    "status": "feature_complete",
    "progress": {
      "viewport_scaffold": "done",
      "loaders_glb_obj_stl": "done",
      "basic_edit_transform": "done",
      "webui_5pane_shell": "done",
      "auth_jwt_scaffold": "done"
    }
  },
  "kpi": {
    "success_rate_target": 0.9,
    "ci_success_rate": 1,
    "test_pass_rate": 1,
    "security_critical": 0,
    "blocker_count": 0
  },
  "schedule": {
    "days": [
      "Mon",
      "Tue",
      "Wed",
      "Thu",
      "Fri"
    ],
    "start_time": "02:00",
    "duration_minutes": 240,
    "timezone": "Asia/Tokyo",
    "note": "月〜金 02:00 JST 起動、240分（4時間）セッション"
  },
  "execution": {
    "max_duration_minutes": 240,
    "repair_count": 0,
    "max_repair": 3,
    "same_error_limit": 2,
    "phase": "Verify",
    "last_session_summary": "Session 2026-05-29: Issue #238 E2E 連鎖失敗の真因を特定・修正。ProjectOut の必須 tags フィールドを欠いたモック (MOCK_PROJECT/NEW_PROJECT/OWNER_PROJECT) が ProjectPanel の p.tags.map で TypeError → 46 テスト連鎖失敗。3 モックを契約準拠に修正し全 173 E2E pass。PR #239 全 CI green で squash merge (main の赤解消、Issue #238 close)。Issue #240 K8s kustomize base を新規作成 (PR #241 open): namespace/configmap/secret/postgres/redis/minio/backend + kustomization + ADR-0004 + README。実バグ 2 件修正 (不正 base64 Secret → stringData、$(VAR) 展開不能な DATABASE_URL を backend env へ移動)。自動セキュリティレビュー 5 件は ADR backlog + Issue #242 で追跡、imagePullPolicy のみ即時適用。PR #241 は CI 実行中で未 merge (再開ポイント)。",
    "current_session_start_at": "2026-05-29T01:52:10.225Z",
    "last_trigger": "manual",
    "last_cron_session_id": "20260527-020001-ArcSphere3D",
    "last_stop_at": "2026-05-29T10:23:30.574Z"
  },
  "automation": {
    "auto_issue_generation": true,
    "self_evolution": true
  },
  "stable": {
    "consecutive_success": 8,
    "target_n": 3,
    "stable_achieved": true,
    "last_green_run_id": "26050580680"
  },
  "completed_issues": [
    "feat/issue-66-multi-owner-last-owner-protection",
    "test/e2e-coverage-62-to-81",
    "feat/cad-panel-three-js-primitives",
    "feat/issue-61-rbac-3tier",
    "fix/issue-62-nul-bytes-text-fields",
    "feat/issue-58-readme-e2e-coverage",
    "fix/schemathesis-422-alignment-openapi",
    "chore/download-artifact-v4-to-v5",
    "test/e2e-coverage-40-to-49",
    "db/alembic-migration-0003-alignments",
    "fix/schemathesis-422-alignment-openapi",
    "chore/download-artifact-v4-to-v5",
    "test/e2e-coverage-40-to-49",
    "db/alembic-migration-0003-alignments",
    "feat/s3-minio-bucket-init",
    "chore/integration-test-expand",
    "docs/readme-feature-table-update",
    "deps/types-proj4-patch",
    "deps/types-node-22-to-25",
    "q3/backend-alignment-crud-api",
    "feat/rbac-member-access",
    "feat/vertical-alignment-api",
    "q3/vertical-alignment-vip-panel",
    "q2/alignment-panel-ip-method",
    "q2/earthwork-panel-cut-fill",
    "q2/terrain-tin-delaunator",
    "q1/gis-maplibre",
    "q1/measure-tool",
    "q1/pointcloud-las",
    "scaffold/monorepo",
    "frontend/vite-react-three",
    "frontend/loaders-gltf-obj-stl",
    "backend/fastapi-skeleton",
    "backend/jwt-auth-scaffold",
    "infra/docker-compose",
    "ci/github-actions",
    "ci/pre-commit",
    "ci/eslint9-flat-config",
    "verify/lint-typecheck-build",
    "docs/architecture-roadmap-security-adr",
    "github/remote-create-push",
    "frontend/transform-gizmo-translate-rotate-scale",
    "fix/eslint-no-redeclare-viewporttoolbar",
    "fix/vite-build-webifc-iife-sourcemap",
    "deps/zustand-v5-react-hooks-plugin-v7",
    "deps/typescript-v6-deferred",
    "feat/issue-22-jwt-rs256-jwks-contract-tests",
    "fix/issue-53-download-artifact-v7",
    "feat/issue-55-rate-limiting",
    "security/issue-180-jwt-immutable-userid",
    "feat/issue-225-project-archive",
    "fix/issue-openapi-notifications-401",
    "fix/openapi-tags-409-conflict",
    "fix/issue-238-e2e-mock-contract-tags"
  ],
  "blocked_issues": [],
  "learning": {
    "failure_patterns": [
      {
        "id": "passlib-bcrypt4-abi",
        "where": "backend/app/security.py",
        "fixed_by": "drop passlib, use bcrypt directly with 72-byte byte-slice cap",
        "memory": "feedback-passlib-dead"
      },
      {
        "id": "emailstr-local-tld",
        "where": "backend/app/routers/auth.py + tests + README",
        "fixed_by": "demo@arcsphere3d.local -> demo@arcsphere3d.dev, pydantic[email] extras",
        "memory": "feedback-emailstr-local-tld"
      },
      {
        "id": "three-vite-oom",
        "where": "frontend/vite.config.ts",
        "fixed_by": "manualChunks vendor-three/vendor-react/vendor + max-old-space-size",
        "memory": "feedback-three-bundle-split"
      },
      {
        "id": "fastapi-on_event-deprecation",
        "where": "backend/app/main.py",
        "fixed_by": "rewrite with @asynccontextmanager lifespan",
        "memory": "feedback-fastapi-lifespan"
      },
      {
        "id": "three-r169-transformcontrols-not-object3d",
        "where": "frontend/src/features/viewport/useThreeScene.ts",
        "fixed_by": "scene.add(tc.getHelper()) — r169 で Controls 基底に分離。scene には helper だけ追加",
        "memory": "feedback-three-r169-controls-split"
      },
      {
        "id": "eslint9-flat-config-missing",
        "where": "frontend/ (ESLint 9 + .eslintrc 不在)",
        "fixed_by": "eslint.config.js (flat config) を作成。@ts-eslint + react-hooks + react-refresh を最小構成で",
        "memory": "feedback-eslint9-flat-config"
      },
      {
        "id": "rollup-native-bad-alloc",
        "where": "frontend/vite.config.ts",
        "fixed_by": "sourcemap: false — rollup Rust バイナリが vendor-three (661kB) の sourcemap を in-memory 生成する際に std::bad_alloc でクラッシュ。esbuild minify に切り替え、web-ifc を IIFE として public/ から配信",
        "memory": "feedback-three-bundle-split"
      },
      {
        "id": "react-hooks-v7-compiler-rules",
        "where": "frontend/eslint.config.js",
        "fixed_by": "eslint-plugin-react-hooks v7 は React Compiler ルール (immutability / set-state-in-effect) をデフォルト有効化。Three.js の命令的ミューテーションと useEffect→setState ブリッジパターンが誤検出されるため off に設定",
        "memory": ""
      },
      {
        "id": "schemathesis-fastapi-400-vs-422",
        "where": "backend/app/routers/alignments.py + tests/test_openapi.py",
        "fixed_by": "FastAPI 0.136+ は JSON body parse error を 400 で返す (以前は 422)。OpenAPI spec に 400 と 422 の両レスポンスを宣言する必要あり。また schemathesis 4.x の hypothesis filter_too_much は suppress_health_check でサプレス",
        "memory": ""
      },
      {
        "id": "boto3-connect-timeout-ci-hang",
        "where": "backend/app/s3.py",
        "fixed_by": "Config(connect_timeout=3, retries={'max_attempts': 0}) を boto3 client に設定。未設定だと S3 unreachable 時に TCP timeout (60s) まで blocking し、schemathesis ASGI lifespan でテストが 10+ 分ハングする",
        "memory": ""
      }
    ],
    "success_patterns": [
      {
        "at": "2026-05-29T10:23:30.585Z",
        "summary": "Session 2026-05-29: Issue #238 E2E 連鎖失敗の真因を特定・修正。ProjectOut の必須 tags フィールドを欠いたモック (MOCK_PROJECT/NEW_PROJECT/OWNER_PROJECT) が ProjectPanel の p.tags.map で TypeError → 46 テスト連鎖失敗。3 モックを契約準拠に修正し全 173 E2E "
      },
      {
        "at": "2026-05-19T17:52:11.583Z",
        "summary": "Build session 2026-05-19: Issue #66 (multi-owner model + last-owner protection) — create_project now auto-adds owner to project_members; count_owners(); remove_member returns None→409 for last owner; "
      },
      {
        "at": "2026-05-18T17:55:29.120Z",
        "summary": "Bootstrap session: scaffolded monorepo (frontend Vite+React+TS+Three.js, backend FastAPI+Pydantic v2+bcrypt direct, docker-compose, CI on GitHub Actions, pre-commit). Verify: backend ruff/format/pytes"
      },
      {
        "at": "2026-05-18T17:51:47.386Z",
        "summary": "Bootstrap session: scaffolded monorepo (frontend Vite+React+TS+Three.js, backend FastAPI+Pydantic v2+bcrypt direct, docker-compose, CI on GitHub Actions, pre-commit). Verify: backend ruff/format/pytes"
      },
      {
        "at": "2026-05-18T17:14:31.400Z",
        "summary": "Bootstrap session: scaffolded monorepo (frontend Vite+React+TS+Three.js, backend FastAPI+Pydantic v2+bcrypt direct, docker-compose, CI on GitHub Actions, pre-commit). Verify: backend ruff/format/pytes"
      },
      {
        "at": "2026-05-16T12:27:00.686Z",
        "summary": "Bootstrap session: scaffolded monorepo (frontend Vite+React+TS+Three.js, backend FastAPI+Pydantic v2+bcrypt direct, docker-compose, CI on GitHub Actions, pre-commit). Verify: backend ruff/format/pytes"
      },
      {
        "at": "2026-05-16T12:24:24.686Z",
        "summary": "Bootstrap session: scaffolded monorepo (frontend Vite+React+TS+Three.js, backend FastAPI+Pydantic v2+bcrypt direct, docker-compose, CI on GitHub Actions, pre-commit). Verify: backend ruff/format/pytes"
      },
      {
        "at": "2026-05-16T12:22:15.390Z",
        "summary": "Bootstrap session: scaffolded monorepo (frontend Vite+React+TS+Three.js, backend FastAPI+Pydantic v2+bcrypt direct, docker-compose, CI on GitHub Actions, pre-commit). Verify: backend ruff/format/pytes"
      },
      {
        "at": "2026-05-16T10:04:29.686Z",
        "summary": "Bootstrap session: scaffolded monorepo (frontend Vite+React+TS+Three.js, backend FastAPI+Pydantic v2+bcrypt direct, docker-compose, CI on GitHub Actions, pre-commit). Verify: backend ruff/format/pytes"
      },
      {
        "at": "2026-05-16T09:28:56.693Z",
        "summary": "Bootstrap session: scaffolded monorepo (frontend Vite+React+TS+Three.js, backend FastAPI+Pydantic v2+bcrypt direct, docker-compose, CI on GitHub Actions, pre-commit). Verify: backend ruff/format/pytes"
      },
      {
        "at": "2026-05-16T09:19:11.108Z",
        "summary": "Bootstrap session: scaffolded monorepo (frontend Vite+React+TS+Three.js, backend FastAPI+Pydantic v2+bcrypt direct, docker-compose, CI on GitHub Actions, pre-commit). Verify: backend ruff/format/pytes"
      },
      {
        "at": "2026-05-16T09:16:43.784Z",
        "summary": "Bootstrap session: scaffolded monorepo (frontend Vite+React+TS+Three.js, backend FastAPI+Pydantic v2+bcrypt direct, docker-compose, CI on GitHub Actions, pre-commit). Verify: backend ruff/format/pytes"
      },
      "verify-before-commit: ruff + format + mypy + pytest + tsc + vite build をすべて green にしてから git stage",
      "topical-commit-split: 単一 big bang ではなく scaffold/feat/ci/docs に分けて bisect 効率を維持"
    ],
    "usage_history": {
      "agents": {
        "Explore": {
          "call_count": 2,
          "last_used": "2026-05-16T09:32:52.191Z",
          "last_description": "バックエンド・インフラ現状調査"
        },
        "_total_agent_calls": 3,
        "_last_agent_call_at": "2026-05-16T09:39:22.057Z",
        "Plan": {
          "call_count": 1,
          "last_used": "2026-05-16T09:39:22.057Z",
          "last_description": "年度別ロードマップ設計"
        }
      }
    }
  },
  "quality_gates": {
    "lint": {
      "warning_threshold": 10,
      "error_threshold": 0
    },
    "coverage": {
      "line_min": 70,
      "changed_files_min": 80
    }
  },
  "stack": {
    "frontend": [
      "React 18",
      "TypeScript 5",
      "Vite 5",
      "TailwindCSS",
      "Zustand",
      "Three.js 0.169"
    ],
    "backend": [
      "FastAPI 0.115",
      "Pydantic v2",
      "SQLAlchemy 2 (post-MVP)",
      "Alembic (post-MVP)",
      "Uvicorn",
      "bcrypt 4.x direct"
    ],
    "storage": [
      "PostgreSQL 16",
      "MinIO",
      "Redis 7"
    ],
    "auth": [
      "JWT RS256 (asymmetric keypair, ADR-0003)",
      "OAuth2 / Microsoft Entra ID SSO (post-MVP)"
    ],
    "infra": [
      "Docker Compose (MVP)",
      "Kubernetes (future ADR-0003)"
    ],
    "ci": [
      "GitHub Actions",
      "CodeQL",
      "Dependabot",
      "pre-commit (ruff/prettier/gitleaks)",
      "CodeRabbit",
      "Codex Review"
    ]
  },
  "github": {
    "repo": "Kensan196948G/ArcSphere3D",
    "base_branch": "main",
    "current_branch": "main",
    "last_pr": 236,
    "remote_configured": true
  },
  "next_session_hints": {
    "priority_order": [
      "Feature: 通知システム (Toast / WebSocket push通知)",
      "Feature: プロジェクト共有UI (メンバー招待 + RBAC ロール表示)",
      "Feature: ユーザープロフィール編集 (メール変更・パスワード変更)",
      "Quality: schemathesis property-based テスト拡充",
      "Infra: Kubernetes manifest 初期構成 (ADR-0003 フォローアップ)"
    ],
    "resume_note": "PR #236 (schemathesis conformance fix: 通知 401 + タグ 409) CI待ち。マージ後は次の Issue (通知 Toast/WebSocket push、プロフィール編集など) を選定して開発継続。"
  },
  "compact": {
    "last_pre_compact_at": "2026-05-18T06:45:30.588Z"
  },
  "dreaming": {
    "patterns": [],
    "curated_memories": [],
    "recurring_mistakes": [],
    "last_dreaming_run": null,
    "dreaming_enabled": false
  },
  "warnings": [
    {
      "at": "2026-05-16T09:16:43.774Z",
      "kind": "verify_subagent_missing",
      "message": "Verify フェーズで qa / security-reviewer / e2e-runner SubAgent が一度も起動されませんでした。STABLE 判定の必要条件を満たしていない可能性があります。",
      "phase": "Verify",
      "required": [
        "qa",
        "security-reviewer",
        "e2e-runner"
      ]
    },
    {
      "at": "2026-05-16T09:16:43.784Z",
      "kind": "tdd_required",
      "message": "テスト未整備の変更が 9 件あります。/tdd または tdd-guide agent で対応してください。",
      "files": [
        "backend/app/config.py",
        "backend/app/routers/auth.py",
        "backend/app/routers/files.py",
        "backend/app/routers/projects.py",
        "backend/app/security.py",
        "backend/tests/conftest.py",
        "backend/tests/test_openapi.py",
        "backend/tests/test_security_invariants.py",
        "frontend/src/features/viewport/useThreeScene.ts"
      ],
      "truncated": false
    },
    {
      "at": "2026-05-16T09:19:11.098Z",
      "kind": "verify_subagent_missing",
      "message": "Verify フェーズで qa / security-reviewer / e2e-runner SubAgent が一度も起動されませんでした。STABLE 判定の必要条件を満たしていない可能性があります。",
      "phase": "Verify",
      "required": [
        "qa",
        "security-reviewer",
        "e2e-runner"
      ]
    },
    {
      "at": "2026-05-16T09:19:11.108Z",
      "kind": "tdd_required",
      "message": "テスト未整備の変更が 9 件あります。/tdd または tdd-guide agent で対応してください。",
      "files": [
        "backend/app/config.py",
        "backend/app/routers/auth.py",
        "backend/app/routers/files.py",
        "backend/app/routers/projects.py",
        "backend/app/security.py",
        "backend/tests/conftest.py",
        "backend/tests/test_openapi.py",
        "backend/tests/test_security_invariants.py",
        "frontend/src/features/viewport/useThreeScene.ts"
      ],
      "truncated": false
    },
    {
      "at": "2026-05-16T09:28:56.684Z",
      "kind": "verify_subagent_missing",
      "message": "Verify フェーズで qa / security-reviewer / e2e-runner SubAgent が一度も起動されませんでした。STABLE 判定の必要条件を満たしていない可能性があります。",
      "phase": "Verify",
      "required": [
        "qa",
        "security-reviewer",
        "e2e-runner"
      ]
    },
    {
      "at": "2026-05-16T09:28:56.693Z",
      "kind": "tdd_required",
      "message": "テスト未整備の変更が 10 件あります。/tdd または tdd-guide agent で対応してください。",
      "files": [
        "backend/app/routers/files.py",
        "backend/app/routers/projects.py",
        "frontend/src/app/layout/RightPanel.tsx",
        "frontend/src/features/bim/IFCPropertyPanel.tsx",
        "frontend/src/features/bim/IFCSpatialTree.tsx",
        "frontend/src/features/viewport/FileLoader.tsx",
        "frontend/src/features/viewport/ifcLoader.ts",
        "frontend/src/features/viewport/loaders.ts",
        "frontend/src/features/viewport/useThreeScene.ts",
        "frontend/src/state/ifcStore.ts"
      ],
      "truncated": false
    },
    {
      "at": "2026-05-16T10:04:29.674Z",
      "kind": "verify_subagent_missing",
      "message": "Verify フェーズで qa / security-reviewer / e2e-runner SubAgent が一度も起動されませんでした。STABLE 判定の必要条件を満たしていない可能性があります。",
      "phase": "Verify",
      "required": [
        "qa",
        "security-reviewer",
        "e2e-runner"
      ]
    },
    {
      "at": "2026-05-16T10:04:29.686Z",
      "kind": "tdd_required",
      "message": "テスト未整備の変更が 19 件あります。/tdd または tdd-guide agent で対応してください。",
      "files": [
        "backend/app/routers/files.py",
        "backend/app/routers/projects.py",
        "frontend/public/maplibre-gl/maplibre-gl-worker.js",
        "frontend/public/maplibre-gl/maplibre-gl.js",
        "frontend/src/app/layout/LeftMenu.tsx",
        "frontend/src/app/layout/RightPanel.tsx",
        "frontend/src/features/bim/IFCPropertyPanel.tsx",
        "frontend/src/features/bim/IFCSpatialTree.tsx",
        "frontend/src/features/gis/GisPanel.tsx",
        "frontend/src/features/gis/useGisMap.ts",
        "frontend/src/features/viewport/FileLoader.tsx",
        "frontend/src/features/viewport/ifcLoader.ts",
        "frontend/src/features/viewport/ifcProperties.ts",
        "frontend/src/features/viewport/loaders.ts",
        "frontend/src/features/viewport/useThreeScene.ts",
        "frontend/src/state/gisStore.ts",
        "frontend/src/state/ifcStore.ts",
        "frontend/src/state/uiStore.ts",
        "frontend/vite.config.ts"
      ],
      "truncated": false
    },
    {
      "at": "2026-05-16T12:22:15.379Z",
      "kind": "verify_subagent_missing",
      "message": "Verify フェーズで qa / security-reviewer / e2e-runner SubAgent が一度も起動されませんでした。STABLE 判定の必要条件を満たしていない可能性があります。",
      "phase": "Verify",
      "required": [
        "qa",
        "security-reviewer",
        "e2e-runner"
      ]
    },
    {
      "at": "2026-05-16T12:22:15.390Z",
      "kind": "tdd_required",
      "message": "テスト未整備の変更が 19 件あります。/tdd または tdd-guide agent で対応してください。",
      "files": [
        "backend/app/db/crud.py",
        "backend/app/models/alignment.py",
        "backend/app/routers/alignments.py",
        "backend/app/schemas.py",
        "backend/tests/conftest.py",
        "backend/tests/test_alignments.py",
        "frontend/src/app/layout/RightPanel.tsx",
        "frontend/src/features/alignment/AlignmentPanel.tsx",
        "frontend/src/features/alignment/VerticalAlignmentPanel.tsx",
        "frontend/src/features/alignment/useAlignment.ts",
        "frontend/src/features/alignment/useVertical.ts",
        "frontend/src/features/earthwork/EarthworkPanel.tsx",
        "frontend/src/features/terrain/TerrainPanel.tsx",
        "frontend/src/features/terrain/useTinSurface.ts",
        "frontend/src/lib/api.ts",
        "frontend/src/state/alignmentStore.ts",
        "frontend/src/state/earthworkStore.ts",
        "frontend/src/state/terrainStore.ts",
        "frontend/src/state/verticalStore.ts"
      ],
      "truncated": false
    },
    {
      "at": "2026-05-16T12:24:24.676Z",
      "kind": "verify_subagent_missing",
      "message": "Verify フェーズで qa / security-reviewer / e2e-runner SubAgent が一度も起動されませんでした。STABLE 判定の必要条件を満たしていない可能性があります。",
      "phase": "Verify",
      "required": [
        "qa",
        "security-reviewer",
        "e2e-runner"
      ]
    },
    {
      "at": "2026-05-16T12:24:24.686Z",
      "kind": "tdd_required",
      "message": "テスト未整備の変更が 19 件あります。/tdd または tdd-guide agent で対応してください。",
      "files": [
        "backend/app/db/crud.py",
        "backend/app/models/alignment.py",
        "backend/app/routers/alignments.py",
        "backend/app/schemas.py",
        "backend/tests/conftest.py",
        "backend/tests/test_alignments.py",
        "frontend/src/app/layout/RightPanel.tsx",
        "frontend/src/features/alignment/AlignmentPanel.tsx",
        "frontend/src/features/alignment/VerticalAlignmentPanel.tsx",
        "frontend/src/features/alignment/useAlignment.ts",
        "frontend/src/features/alignment/useVertical.ts",
        "frontend/src/features/earthwork/EarthworkPanel.tsx",
        "frontend/src/features/terrain/TerrainPanel.tsx",
        "frontend/src/features/terrain/useTinSurface.ts",
        "frontend/src/lib/api.ts",
        "frontend/src/state/alignmentStore.ts",
        "frontend/src/state/earthworkStore.ts",
        "frontend/src/state/terrainStore.ts",
        "frontend/src/state/verticalStore.ts"
      ],
      "truncated": false
    },
    {
      "at": "2026-05-16T12:27:00.676Z",
      "kind": "verify_subagent_missing",
      "message": "Verify フェーズで qa / security-reviewer / e2e-runner SubAgent が一度も起動されませんでした。STABLE 判定の必要条件を満たしていない可能性があります。",
      "phase": "Verify",
      "required": [
        "qa",
        "security-reviewer",
        "e2e-runner"
      ]
    },
    {
      "at": "2026-05-16T12:27:00.686Z",
      "kind": "tdd_required",
      "message": "テスト未整備の変更が 19 件あります。/tdd または tdd-guide agent で対応してください。",
      "files": [
        "backend/app/db/crud.py",
        "backend/app/models/alignment.py",
        "backend/app/routers/alignments.py",
        "backend/app/schemas.py",
        "backend/tests/conftest.py",
        "backend/tests/test_alignments.py",
        "frontend/src/app/layout/RightPanel.tsx",
        "frontend/src/features/alignment/AlignmentPanel.tsx",
        "frontend/src/features/alignment/VerticalAlignmentPanel.tsx",
        "frontend/src/features/alignment/useAlignment.ts",
        "frontend/src/features/alignment/useVertical.ts",
        "frontend/src/features/earthwork/EarthworkPanel.tsx",
        "frontend/src/features/terrain/TerrainPanel.tsx",
        "frontend/src/features/terrain/useTinSurface.ts",
        "frontend/src/lib/api.ts",
        "frontend/src/state/alignmentStore.ts",
        "frontend/src/state/earthworkStore.ts",
        "frontend/src/state/terrainStore.ts",
        "frontend/src/state/verticalStore.ts"
      ],
      "truncated": false
    },
    {
      "at": "2026-05-18T17:14:31.398Z",
      "kind": "tdd_required",
      "message": "テスト未整備の変更が 7 件あります。/tdd または tdd-guide agent で対応してください。",
      "files": [
        "backend/app/ratelimit.py",
        "backend/app/routers/auth.py",
        "backend/app/schemas.py",
        "backend/tests/conftest.py",
        "backend/tests/test_auth.py",
        "backend/tests/test_openapi.py",
        "backend/tests/test_schemas_nul_bytes.py"
      ],
      "truncated": false
    },
    {
      "at": "2026-05-18T17:51:47.384Z",
      "kind": "tdd_required",
      "message": "テスト未整備の変更が 11 件あります。/tdd または tdd-guide agent で対応してください。",
      "files": [
        "backend/app/db/crud.py",
        "backend/app/ratelimit.py",
        "backend/app/routers/auth.py",
        "backend/app/routers/project_members.py",
        "backend/app/routers/projects.py",
        "backend/app/schemas.py",
        "backend/tests/conftest.py",
        "backend/tests/test_auth.py",
        "backend/tests/test_openapi.py",
        "backend/tests/test_rbac_3tier.py",
        "backend/tests/test_schemas_nul_bytes.py"
      ],
      "truncated": false
    },
    {
      "at": "2026-05-18T17:55:29.118Z",
      "kind": "tdd_required",
      "message": "テスト未整備の変更が 11 件あります。/tdd または tdd-guide agent で対応してください。",
      "files": [
        "backend/app/db/crud.py",
        "backend/app/ratelimit.py",
        "backend/app/routers/auth.py",
        "backend/app/routers/project_members.py",
        "backend/app/routers/projects.py",
        "backend/app/schemas.py",
        "backend/tests/conftest.py",
        "backend/tests/test_auth.py",
        "backend/tests/test_openapi.py",
        "backend/tests/test_rbac_3tier.py",
        "backend/tests/test_schemas_nul_bytes.py"
      ],
      "truncated": false
    },
    {
      "at": "2026-05-19T17:52:11.581Z",
      "kind": "tdd_required",
      "message": "テスト未整備の変更が 15 件あります。/tdd または tdd-guide agent で対応してください。",
      "files": [
        "backend/alembic/versions/20260519_0006_backfill_owner_members.py",
        "backend/app/db/crud.py",
        "backend/app/routers/project_members.py",
        "backend/tests/test_project_members.py",
        "backend/tests/test_rbac_3tier.py",
        "frontend/src/app/layout/BottomConsole.tsx",
        "frontend/src/app/layout/LeftMenu.tsx",
        "frontend/src/app/layout/RightPanel.tsx",
        "frontend/src/features/cad/CadPanel.tsx",
        "frontend/src/features/cad/cadPrimitives.ts",
        "frontend/src/features/members/MembersPanel.tsx",
        "frontend/src/features/project/ProjectPanel.tsx",
        "frontend/src/lib/api.ts",
        "frontend/src/state/projectStore.ts",
        "frontend/src/state/uiStore.ts"
      ],
      "truncated": false
    },
    {
      "at": "2026-05-29T10:23:30.574Z",
      "kind": "verify_subagent_missing",
      "message": "Verify フェーズで qa / security-reviewer / e2e-runner SubAgent が一度も起動されませんでした。STABLE 判定の必要条件を満たしていない可能性があります。",
      "phase": "Verify",
      "required": [
        "qa",
        "security-reviewer",
        "e2e-runner"
      ]
    }
  ]
}
